ScrobblIES/1_Scrape.py
ScrobblIES/2_Analyse.py
ScrobblIES/3_Visualise_Maps.py
ScrobblIES/4_Visualise_Tags.py
ScrobblIES/__init__.py
ScrobblIES-0.0.1.dist-info/METADATA
ScrobblIES-0.0.1.dist-info/WHEEL
ScrobblIES-0.0.1.dist-info/top_level.txt
ScrobblIES-0.0.1.dist-info/RECORD
