Metadata-Version: 2.1
Name: ScrobblIES
Version: 0.0.1
Summary: Offers a set of tools for scraping from Last.fm
Home-page: https://github.com/petrpham/ScrobblIES
Author: Petr Pham & Matěj Kovář
Author-email: UNKNOWN
License: unlicense
Platform: UNKNOWN
